gradiator/__init__.py
gradiator/_version.py
gradiator/gradiator.py
gradiator/utils.py
gradiator-0.0.1.dev14.dist-info/LICENSE
gradiator-0.0.1.dev14.dist-info/METADATA
gradiator-0.0.1.dev14.dist-info/WHEEL
gradiator-0.0.1.dev14.dist-info/entry_points.txt
gradiator-0.0.1.dev14.dist-info/top_level.txt
gradiator-0.0.1.dev14.dist-info/RECORD
