Metadata-Version: 2.1
Name: gradiator
Version: 0.0.1.dev14
Summary: turn covariance matrices into brain gradients
Author: Leonard Sasse
Author-email: l.sasse@fz-juelich.de
Project-URL: repository, https://github.com/LeSasse/gradiator
Keywords: neuroimaging
Classifier: Development Status :: 4 - Beta
Classifier: Intended Audience :: Science/Research
Classifier: Intended Audience :: Developers
Classifier: License :: OSI Approved
Classifier: Natural Language :: English
Classifier: Topic :: Software Development
Classifier: Topic :: Scientific/Engineering
Classifier: Topic :: Scientific/Engineering :: Bio-Informatics
Classifier: Operating System :: OS Independent
Classifier: Programming Language :: Python :: 3
Requires-Python: >=3.7
License-File: LICENSE
Requires-Dist: nilearn (<1.0,>=0.9.0)
Requires-Dist: brainspace
Provides-Extra: dev
Requires-Dist: tox ; extra == 'dev'
